{
    "read_files": "[ /beegfs3/ikelava/H9_35d_concat/H9_0502_35d_DHT_concatenated_2019.fq.gz ]",
    "expected_format": "SR",
    "compatible_fragment_ratio": 1.0,
    "num_compatible_fragments": 14971811,
    "num_assigned_fragments": 14971811,
    "num_frags_with_consistent_mappings": 14971711,
    "num_frags_with_inconsistent_or_orphan_mappings": 278,
    "MSF": 0,
    "OSF": 0,
    "ISF": 0,
    "MSR": 0,
    "OSR": 0,
    "ISR": 0,
    "SF": 278,
    "SR": 14971711,
    "MU": 0,
    "OU": 0,
    "IU": 0,
    "U": 0
}